package/__init__.py
package/missingValTarit.py
Tarit_Missing_Values-1.0.0.dist-info/LICENSE.txt
Tarit_Missing_Values-1.0.0.dist-info/METADATA
Tarit_Missing_Values-1.0.0.dist-info/WHEEL
Tarit_Missing_Values-1.0.0.dist-info/entry_points.txt
Tarit_Missing_Values-1.0.0.dist-info/top_level.txt
Tarit_Missing_Values-1.0.0.dist-info/RECORD
